arcor2_calibration/VERSION
arcor2_calibration/__init__.py
arcor2_calibration/calibration.py
arcor2_calibration/py.typed
arcor2_calibration/quaternions.py
arcor2_calibration/robot.py
arcor2_calibration/scripts/__init__.py
arcor2_calibration/scripts/calibration.py
arcor2_calibration-1.2.0.dist-info/METADATA
arcor2_calibration-1.2.0.dist-info/WHEEL
arcor2_calibration-1.2.0.dist-info/entry_points.txt
arcor2_calibration-1.2.0.dist-info/namespace_packages.txt
arcor2_calibration-1.2.0.dist-info/top_level.txt
arcor2_calibration-1.2.0.dist-info/RECORD
