Metadata-Version: 2.1
Name: arcor2-calibration
Version: 1.2.0
Summary: ARCOR2 Calibration
Author: Robo@FIT
Author-email: imaterna@fit.vut.cz
License: LGPL
Classifier: Development Status :: 3 - Alpha
Classifier: Intended Audience :: Developers
Classifier: Topic :: Software Development :: Build Tools
Classifier: License :: OSI Approved :: GNU Lesser General Public License v3 (LGPLv3)
Classifier: Programming Language :: Python :: 3.11
Classifier: Natural Language :: English
Classifier: Topic :: Scientific/Engineering
Requires-Python: ==3.11.*
Requires-Dist: Flask (~=3.0.2)
Requires-Dist: Pillow (~=10.2.0)
Requires-Dist: PyYAML (~=6.0.1)
Requires-Dist: arcor2-calibration-data (~=1.1.0)
Requires-Dist: arcor2 (~=1.3.0)
Requires-Dist: dataclasses-jsonschema[apispec,fast-dateparsing,fast-validation] (~=2.16.0)
Requires-Dist: numpy-quaternion[numba,scipy] (~=2023.0.3)
Requires-Dist: numpy (~=1.26.4)
Requires-Dist: open3d (==0.18.0)
Requires-Dist: opencv-contrib-python (~=4.9.0.80)
Requires-Dist: setuptools (~=69.2.0)
Requires-Dist: types-PyYAML (==6.0.12.20240311)
Requires-Dist: urdfpy (~=0.0.22)
